oauthverifyserver.py
setup.py
pyoauthverifyserver.egg-info/PKG-INFO
pyoauthverifyserver.egg-info/SOURCES.txt
pyoauthverifyserver.egg-info/dependency_links.txt
pyoauthverifyserver.egg-info/top_level.txt