Metadata-Version: 1.0
Name: pyoauthverifyserver
Version: 0.1.2
Summary: A simple server to receive an OAuth Verification to simplify asking permission for desktop and console applications
Home-page: https://bitbucket.org/russellhay/pyoauthverifyserver
Author: Russell Hay
Author-email: me@russellhay.com
License: UNKNOWN
Platform: UNKNOWN
